solcx_select/__init__.py
solcx_select/solcx_select.py
solcx_select-0.1.0.dist-info/LICENSE
solcx_select-0.1.0.dist-info/METADATA
solcx_select-0.1.0.dist-info/WHEEL
solcx_select-0.1.0.dist-info/entry_points.txt
solcx_select-0.1.0.dist-info/top_level.txt
solcx_select-0.1.0.dist-info/RECORD
