Metadata-Version: 2.1
Name: solcx-select
Version: 0.1.0
Summary: Console script to symlink py-solc-x installed solc binaries to allow access from the command line in the style of solc-select
Author-email: c mark0v <cmark0v@protonmail.com>
License: GPLv3
Keywords: solc,solcx,solidity,ethereum
Requires-Python: >=3.6
License-File: LICENSE
Requires-Dist: py-solc-x
